{
  "duration": 6.768,
  "word_timestamps": [
    {
      "word": "Imagine",
      "start": 0.0,
      "end": 0.21339999999999998
    },
    {
      "word": "you",
      "start": 0.21339999999999998,
      "end": 0.42679999999999996
    },
    {
      "word": "re",
      "start": 0.42679999999999996,
      "end": 0.6401999999999999
    },
    {
      "word": "standing",
      "start": 0.6401999999999999,
      "end": 0.8535999999999999
    },
    {
      "word": "on",
      "start": 0.8535999999999999,
      "end": 1.067
    },
    {
      "word": "a",
      "start": 1.067,
      "end": 1.2804
    },
    {
      "word": "skateboard",
      "start": 1.2804,
      "end": 1.4938
    },
    {
      "word": "and",
      "start": 1.7938,
      "end": 2.0072
    },
    {
      "word": "you",
      "start": 2.0072,
      "end": 2.2206
    },
    {
      "word": "push",
      "start": 2.2206,
      "end": 2.434
    },
    {
      "word": "against",
      "start": 2.434,
      "end": 2.6474
    },
    {
      "word": "a",
      "start": 2.6474,
      "end": 2.8608000000000002
    },
    {
      "word": "wall",
      "start": 2.8608000000000002,
      "end": 3.0742000000000003
    },
    {
      "word": "What",
      "start": 3.5742000000000003,
      "end": 3.7876000000000003
    },
    {
      "word": "happens",
      "start": 3.7876000000000003,
      "end": 4.001
    },
    {
      "word": "You",
      "start": 4.601,
      "end": 4.8144
    },
    {
      "word": "roll",
      "start": 4.8144,
      "end": 5.0278
    },
    {
      "word": "backward",
      "start": 5.0278,
      "end": 5.2412
    },
    {
      "word": "But",
      "start": 5.7412,
      "end": 5.9546
    },
    {
      "word": "why",
      "start": 5.9546,
      "end": 6.168
    }
  ]
}