{
  "duration": 8.592,
  "word_timestamps": [
    {
      "word": "We",
      "start": 0.0,
      "end": 0.31123076923076926
    },
    {
      "word": "can",
      "start": 0.31123076923076926,
      "end": 0.6224615384615385
    },
    {
      "word": "describe",
      "start": 0.6224615384615385,
      "end": 0.9336923076923078
    },
    {
      "word": "gravity",
      "start": 0.9336923076923078,
      "end": 1.244923076923077
    },
    {
      "word": "with",
      "start": 1.244923076923077,
      "end": 1.5561538461538462
    },
    {
      "word": "an",
      "start": 1.5561538461538462,
      "end": 1.8673846153846154
    },
    {
      "word": "equation",
      "start": 1.8673846153846154,
      "end": 2.1786153846153846
    },
    {
      "word": ":",
      "start": 2.1786153846153846,
      "end": 2.489846153846154
    },
    {
      "word": "F",
      "start": 2.489846153846154,
      "end": 2.8010769230769235
    },
    {
      "word": "equals",
      "start": 2.8010769230769235,
      "end": 3.112307692307693
    },
    {
      "word": "G",
      "start": 3.112307692307693,
      "end": 3.4235384615384623
    },
    {
      "word": "times",
      "start": 3.4235384615384623,
      "end": 3.7347692307692317
    },
    {
      "word": "the",
      "start": 3.7347692307692317,
      "end": 4.046000000000001
    },
    {
      "word": "product",
      "start": 4.046000000000001,
      "end": 4.35723076923077
    },
    {
      "word": "of",
      "start": 4.35723076923077,
      "end": 4.668461538461539
    },
    {
      "word": "two",
      "start": 4.668461538461539,
      "end": 4.979692307692308
    },
    {
      "word": "masses",
      "start": 4.979692307692308,
      "end": 5.290923076923077
    },
    {
      "word": "divided",
      "start": 5.290923076923077,
      "end": 5.602153846153846
    },
    {
      "word": "by",
      "start": 5.602153846153846,
      "end": 5.913384615384615
    },
    {
      "word": "the",
      "start": 5.913384615384615,
      "end": 6.224615384615384
    },
    {
      "word": "square",
      "start": 6.224615384615384,
      "end": 6.535846153846153
    },
    {
      "word": "of",
      "start": 6.535846153846153,
      "end": 6.847076923076922
    },
    {
      "word": "the",
      "start": 6.847076923076922,
      "end": 7.158307692307691
    },
    {
      "word": "distance",
      "start": 7.158307692307691,
      "end": 7.46953846153846
    },
    {
      "word": "between",
      "start": 7.46953846153846,
      "end": 7.780769230769229
    },
    {
      "word": "them",
      "start": 7.780769230769229,
      "end": 8.091999999999999
    }
  ]
}